LICENSE
README.md
setup.py
utf8conv/__init__.py
utf8conv.egg-info/PKG-INFO
utf8conv.egg-info/SOURCES.txt
utf8conv.egg-info/dependency_links.txt
utf8conv.egg-info/requires.txt
utf8conv.egg-info/top_level.txt