Metadata-Version: 2.1
Name: utf8conv
Version: 0.0.2
Summary: conv files into utf-8 encoding
Home-page: https://github.com/juju-w/utf8conv
Author: wangkuiju
Author-email: kuijuwang@gmail.com
License: MIT License
Platform: all
Classifier: Programming Language :: Python :: 3
Classifier: License :: OSI Approved :: MIT License
Classifier: Operating System :: OS Independent
Requires-Python: >=3.6
License-File: LICENSE
